{
  "name": "system operator",
  "data": {
    "replace an existing system": {
      "id": 73,
      "nterm": "transition",
      "url": null
    },
    "system scheduled maintenance": {
      "id": 74,
      "nterm": "maintenance",
      "url": null
    },
    "slep": {
      "id": 76,
      "nterm": "operation",
      "url": null
    },
    "manage the migration between systems": {
      "id": 76,
      "nterm": "operation",
      "url": null
    },
    "maintenance process": {
      "id": 74,
      "nterm": "maintenance",
      "url": null
    },
    "system maintenance": {
      "id": 74,
      "nterm": "maintenance",
      "url": null
    },
    "terraphim hello": {
      "id": 77,
      "nterm": "testconcept",
      "url": null
    },
    "service life extension program": {
      "id": 76,
      "nterm": "operation",
      "url": null
    },
    "transition": {
      "id": 73,
      "nterm": "transition",
      "url": null
    },
    "system maintains key functions": {
      "id": 76,
      "nterm": "operation",
      "url": null
    },
    "identify analyze operational problems": {
      "id": 76,
      "nterm": "operation",
      "url": null
    },
    "monitor the services": {
      "id": 76,
      "nterm": "operation",
      "url": null
    },
    "preventive maintenance": {
      "id": 74,
      "nterm": "maintenance",
      "url": null
    },
    "maintenance actions": {
      "id": 76,
      "nterm": "operation",
      "url": null
    },
    "corrective maintenance": {
      "id": 74,
      "nterm": "maintenance",
      "url": null
    },
    "operate the system": {
      "id": 76,
      "nterm": "operation",
      "url": null
    },
    "sustain service": {
      "id": 76,
      "nterm": "operation",
      "url": null
    },
    "system operationally effective": {
      "id": 76,
      "nterm": "operation",
      "url": null
    },
    "maintenance": {
      "id": 74,
      "nterm": "maintenance",
      "url": null
    },
    "hello terraphim": {
      "id": 77,
      "nterm": "testconcept",
      "url": null
    },
    "testconcept": {
      "id": 77,
      "nterm": "testconcept",
      "url": null
    },
    "replace a legacy system": {
      "id": 73,
      "nterm": "transition",
      "url": null
    },
    "maintenance management": {
      "id": 74,
      "nterm": "maintenance",
      "url": null
    },
    "breakdown in services": {
      "id": 76,
      "nterm": "operation",
      "url": null
    },
    "analyze operational problems": {
      "id": 76,
      "nterm": "operation",
      "url": null
    },
    "operation": {
      "id": 76,
      "nterm": "operation",
      "url": null
    },
    "maintenance activities": {
      "id": 74,
      "nterm": "maintenance",
      "url": null
    },
    "operation of system": {
      "id": 76,
      "nterm": "operation",
      "url": null
    },
    "monitor system performance": {
      "id": 76,
      "nterm": "operation",
      "url": null
    },
    "maintaining operational capability": {
      "id": 74,
      "nterm": "maintenance",
      "url": null
    }
  }
}